Laboratorio_2/Ejercicio_2/src/design/BE.sv
`timescale 1ms / 100us


module KBE(// Bounce Elimination module
  input  logic KeyP,
  output logic Data_Available,
  output logic Inhibit
);

always @(KeyP)begin
    #20 // Espera 20 ms
    if (KeyP) begin // si la tecla sigue presionada
      Data_Available = 1;
      Inhibit =1;
    end else begin 
      Data_Available =0;
      Inhibit =0;
    end
end


endmodule

Laboratorio_2/Ejercicio_2/Key-Bounce/src/sim/TB.sv
`timescale 1ms / 100us


module KBE_TB;
    reg KeyP;
    wire Data_Available;
    wire Inhibit;

    KBE be0(
        .KeyP(KeyP),
        .Data_Available(Data_Available),
        .Inhibit(Inhibit)
    );
    initial begin //bloque de pruebas
        KeyP<=0;

        for(int i=0;i<10;i=i+1)begin
            KeyP<=$random;
            #25
            $display("[%0t] key=0x%0h Data Available=0x%0h Inhibit=0x%0h",$time,KeyP,Data_Available,Inhibit);
        end
        #5 $finish;
    end
    initial begin
        $dumpfile("KBE_TB.vcd");
        $dumpvars(0,KBE_TB);
    end

endmodule

Laboratorio_2/Ejercicio_2/src/build/KBE_TB.vcd
$date
	Wed Sep 11 14:14:43 2024
$end
$version
	Icarus Verilog
$end
$timescale
	100us
$end
$scope module KBE_TB $end
$var wire 1 ! Inhibit $end
$var wire 1 " Data_Available $end
$var reg 1 # KeyP $end
$scope module be0 $end
$var wire 1 # KeyP $end
$var reg 1 " Data_Available $end
$var reg 1 ! Inhibit $end
$upscope $end
$scope begin $ivl_for_loop0 $end
$var integer 32 $ i [31:0] $end
$upscope $end
$upscope $end
$enddefinitions $end
$comment Show the parameter values. $end
$dumpall
$end
#0
$dumpvars
b0 $
0#
x"
x!
$end
#200
0!
0"
#250
1#
b1 $
#450
1"
#500
b10 $
#750
b11 $
#1000
b100 $
#1250
b101 $
#1500
b110 $
#1750
0#
b111 $
#1950
0"
#2000
1#
b1000 $
#2200
1"
#2250
b1001 $
#2500
b1010 $
