Laboratorio_1/Ejercicio_5/src/design/ALU.sv
`timescale 1ns / 1ps


module ALUP#(parameter int unsigned WIDTH=4) (//WIDTH ancho de los buses 
  input  logic [WIDTH-1:0] ALUA,
  input  logic [WIDTH-1:0] ALUB,
  input  logic [3:0] ALUControl,
  input logic ALUFlagIn,
  output logic [WIDTH-1:0] ALUResult,
  output logic C,
  output logic Z
);
always_comb begin
    //and 
    //or 
    //suma
    //incremento en 1
    //decremento en 1
    //not
    //resta
    //xor
    //corrimiento izquierda
    //corrimiento derecha
    case (ALUControl)
      'h0:             ALUResult = ALUA & ALUB;//and
      'h1:             ALUResult = ALUA | ALUB;//or
      'h2:             ALUResult = ~((~ALUA+1'b1) + (~ALUB+1'b1));//suma complemento a 2
      'h3: if(ALUFlagIn) ALUResult = ALUB+1;else ALUResult = ALUA+1;//incremento en 1//SI es 0 elije B, si es 1 elije A
      'h4: if(ALUFlagIn) ALUResult = ALUB-1;else ALUResult = ALUA-1;//decremento en 1
      'h5: if(ALUFlagIn)ALUResult = !ALUB;else ALUResult = !ALUA;//not 
      'h6:             ALUResult = (ALUA + (~ALUB+1'b1));//resta complemento a 2
      'h7:             ALUResult = ALUA ^ ALUB;//Xor
      'h8: if(ALUFlagIn)//corrimiento a la izqueirda de A
          ALUResult = (ALUA << ALUB) | ((1 << ALUB) - 1);//corre a la izquierda ALUB bits y los rellena con 1
        else ALUResult = ALUA<<ALUB;//corre a la izquierda y rellena con 0
      'h9: //corrimiento a la derecha de A
        if(ALUFlagIn)
          ALUResult = (ALUA >> ALUB) | (~((1 << (WIDTH - ALUB)) - 1));//mueve a la derecha y rellena con 1
        else ALUResult = ALUA >> ALUB;
        
      default: ALUResult = '0; 
    endcase
  end
  assign Z = (ALUResult!=0) ? 0 : 1;// es 1 si el ALUResult es 0
  assign C = (ALUControl=='h8) ? (WIDTH<ALUB ? 1 : ALUA[WIDTH-ALUB]):(ALUControl=='h9)? (WIDTH<ALUB ? 0 : ALUA[ALUB-1]) : 0;//toma el valor del ultimo digito desplazado por las funciones 'h8 y 'h9
endmodule

Laboratorio_1/Ejercicio_5/src/sim/TB.sv
`timescale 1ns / 1ps


module TB#(parameter int unsigned WIDTH=4);
    //'h0 and 
    //'h1 or 
    //'h2 suma
    //'h3 incremento en 1
    //'h4 decremento en 1
    //'h5 resta
    //'h6 xor
    //'h7 corrimiento izquierda
    //'h8 corrimiento derecha

    reg [WIDTH-1:0] ALUA;
    reg [WIDTH-1:0] ALUB;
    reg [3:0] ALUControl;
    reg ALUFlagIn;
    wire [WIDTH-1:0] ALUResult;//salida 1
    wire C;//salida 2
    wire Z;
    reg [WIDTH-1:0] i;

    ALUP alu0(.ALUA(ALUA),
            .ALUB(ALUB),
            .ALUControl(ALUControl),
            .ALUFlagIn(ALUFlagIn),
            .ALUResult(ALUResult),
            .C(C),
            .Z(Z)
    );
    initial begin //bloque de pruebas
        ALUA<=0;
        ALUB<=0;
        ALUControl <= 'h0;
        ALUFlagIn <= 0;
        //Prueba 'h0
        for (int i =0 ; i<4;i++ ) begin
            ALUA<=$random;
            ALUB<=$random;
            ALUFlagIn <=$random;
            #5 ALUControl<='h1;
            ALUFlagIn <=$random;
            #5 ALUControl<='h2;
            ALUFlagIn <=$random;
            #5 ALUControl<='h3;
            ALUFlagIn <=$random;
            #5 ALUControl<='h4;
            ALUFlagIn <=$random;
            #5 ALUControl<='h5;
            ALUFlagIn <=$random;
            #5 ALUControl<='h6;
            ALUFlagIn <=$random;
            #5 ALUControl<='h7;
            ALUFlagIn <=$random;
            #5 ALUControl<='h8;
            ALUFlagIn <=$random;
            #5 ALUControl<='h9;
            ALUFlagIn <=$random;
            #5;
        end
        #5 $finish;
    end
    initial begin
        $dumpfile("TB.vcd");
        $dumpvars(0,TB);
    end

endmodule

Laboratorio_1/Ejercicio_5/src/build/TB.vcd
$date
	Mon Aug 19 17:40:27 2024
$end
$version
	Icarus Verilog
$end
$timescale
	1ps
$end
$scope module TB $end
$var wire 1 ! Z $end
$var wire 1 " C $end
$var wire 4 # ALUResult [3:0] $end
$var parameter 32 $ WIDTH $end
$var reg 4 % ALUA [3:0] $end
$var reg 4 & ALUB [3:0] $end
$var reg 4 ' ALUControl [3:0] $end
$var reg 1 ( ALUFlagIn $end
$scope module alu0 $end
$var wire 4 ) ALUA [3:0] $end
$var wire 4 * ALUB [3:0] $end
$var wire 4 + ALUControl [3:0] $end
$var wire 1 ( ALUFlagIn $end
$var wire 1 ! Z $end
$var wire 1 " C $end
$var parameter 32 , WIDTH $end
$var reg 4 - ALUResult [3:0] $end
$upscope $end
$scope begin $ivl_for_loop0 $end
$var integer 32 . i [31:0] $end
$upscope $end
$upscope $end
$enddefinitions $end
$comment Show the parameter values. $end
$dumpall
b100 ,
b100 $
$end
#0
$dumpvars
b0 .
b0 -
b0 +
b1 *
b100 )
1(
b0 '
b1 &
b100 %
b0 #
0"
1!
$end
#5000
0!
b101 #
b101 -
b1 '
b1 +
#10000
b100 #
b100 -
b10 '
b10 +
#15000
b10 #
b10 -
b11 '
b11 +
#20000
1!
b0 #
b0 -
b100 '
b100 +
#25000
0(
b101 '
b101 +
#30000
0!
b11 #
b11 -
1(
b110 '
b110 +
#35000
b101 #
b101 -
b111 '
b111 +
#40000
b1000 #
b1000 -
0(
b1000 '
b1000 +
#45000
b1010 #
b1010 -
1(
b1001 '
b1001 +
#50000
1!
b0 #
b0 -
b1100 &
b1100 *
b1101 %
b1101 )
b1 .
#55000
0!
b1101 #
b1101 -
0(
b1 '
b1 +
#60000
b1000 #
b1000 -
1(
b10 '
b10 +
#65000
b1110 #
b1110 -
0(
b11 '
b11 +
#70000
b1011 #
b1011 -
1(
b100 '
b100 +
#75000
1!
b0 #
b0 -
b101 '
b101 +
#80000
0!
b1 #
b1 -
0(
b110 '
b110 +
#85000
1(
b111 '
b111 +
#90000
1!
1"
b0 #
b0 -
0(
b1000 '
b1000 +
#95000
0"
b1001 '
b1001 +
#100000
b101 &
b101 *
b1000 %
b1000 )
b10 .
#105000
0!
b1101 #
b1101 -
1(
b1 '
b1 +
#110000
b1100 #
b1100 -
b10 '
b10 +
#115000
b110 #
b110 -
b11 '
b11 +
#120000
b100 #
b100 -
b100 '
b100 +
#125000
1!
b0 #
b0 -
0(
b101 '
b101 +
#130000
0!
b11 #
b11 -
b110 '
b110 +
#135000
b1101 #
b1101 -
b111 '
b111 +
#140000
1!
1"
b0 #
b0 -
b1000 '
b1000 +
#145000
0"
1(
b1001 '
b1001 +
#150000
1"
0!
b1110 #
b1110 -
b11 &
b11 *
b110 %
b110 )
b11 .
#155000
0"
b111 #
b111 -
b1 '
b1 +
#160000
b1000 #
b1000 -
b10 '
b10 +
#165000
b100 #
b100 -
b11 '
b11 +
#170000
b101 #
b101 -
0(
b100 '
b100 +
#175000
1!
b0 #
b0 -
b101 '
b101 +
#180000
0!
b11 #
b11 -
1(
b110 '
b110 +
#185000
b101 #
b101 -
b111 '
b111 +
#190000
1"
b111 #
b111 -
b1000 '
b1000 +
#195000
1!
b0 #
b0 -
0(
b1001 '
b1001 +
#200000
b100 .
