Laboratorio_2/Ejercicio_2/Interfaz/design/sincronizador.sv
`timescale 1ms / 10ns
module sincronizador (
  input  D0,//fila[0]
  input  D1,//fila[1]
  input  D2,//columna[0]
  input  D3,//columna[1]
  input  clk, //cada vez que exite KeyP
  input  rst, 
  output  logic [3:0]  Q
);

always_ff @(posedge clk, posedge rst) begin
    if (rst) begin
      Q = 0;
    end else begin
      Q[0]=1;
      Q[1]=1;
      Q[2]=0;
      Q[3]=1;
    end
  end
endmodule

Laboratorio_2/Ejercicio_2/Interfaz/design/Contador.sv
`timescale 1ms / 10ns

module contador (
    input inhibit,
    input clk,
    output reg [1:0] out
);

    always @(posedge clk) begin
        if (!inhibit) begin //si se presiona una tecla
            out <= out+1'b1;
        end else
            out <= 0;
    end

endmodule

Laboratorio_2/Ejercicio_2/Interfaz/design/BE.sv
`timescale 1ms / 10ns


module KBE(// Bounce Elimination module
  input  logic KeyP,
  output logic Data_Available,
  output logic inhibit
);
always @(KeyP)begin
    inhibit=1;
    #2 // Espera 2 ms
    if (KeyP) begin // si la tecla sigue presionada
      Data_Available = 0;
      inhibit =0;
    end else begin 
      Data_Available =1;
      inhibit =1;
    end
end


endmodule

Laboratorio_2/Ejercicio_2/Interfaz/design/Interfaz.sv
`timescale 1ms / 10ns

module Interfaz(
    input  logic KeyP,
    input  logic rst,
    input logic clk,
    input logic [1:0] fila,
    input uart_rx,
    output  logic [1:0] columna,
    output logic [3:0] Q,
    output logic [3:0] code,
    output uart_tx
);
wire inhibit;
wire uart_tx1;
wire Data_Available;
wire [1:0] columna1;
wire [3:0] Q1;
reg clk1;

localparam DELAY_FRAMES = 2812;// 27,000,000 (27Mhz) / 9600 Baud rate
localparam HALF_DELAY_WAIT = (DELAY_FRAMES / 2);



KBE b0(
        .KeyP(KeyP),
        .Data_Available(Data_Available),
        .inhibit(inhibit)
);

contador c0(//2bit contador
    .inhibit(inhibit),
    .clk(clk1),
    .out(columna1)
);
sincronizador s0(// sincronizador
    .D0(fila[0]),
    .D1(fila[1]),
    .D2(columna1[0]),
    .D3(columna1[1]),
    .clk(Data_Available),
    .rst(rst),
    .Q(Q1)
);

//Codificador
assign Q=Q1;
assign columna = columna1;

always @(Q1) begin
    case (Q)
        4'b0000: code <= 4'h1;
        4'b0001: code <= 4'h2;
        4'b0010: code <= 4'h3;
        4'b0011: code <= 4'hA;
        4'b0100: code <= 4'h4;
        4'b0101: code <= 4'h5;
        4'b0110: code <= 4'h6;
        4'b0111: code <= 4'hB;
        4'b1000: code <= 4'h7;
        4'b1001: code <= 4'h8;
        4'b1010: code <= 4'h9;
        4'b1011: code <= 4'hC;
        4'b1100: code <= 4'hF;
        4'b1101: code <= 4'h0;
        4'b1110: code <= 4'hE;
        4'b1111: code <= 4'hD;
        default: code <= 4'h0;
    endcase
end

//uart 
reg [3:0] txState = 0;// estado actual
reg [24:0] txCounter = 0;// ciclos de reloj
reg [7:0] dataOut = 0;// byte que se envía
reg txPinRegister = 1;// valor a adjuntar en uart_tx
reg [2:0] txBitNumber = 0;// bit enviando

assign uart_tx = txPinRegister;

// parte a cambiar
reg [7:0] code_uart;
always @(KeyP) begin
    case (Q)
        4'b0000: code_uart <= "1";
        4'b0001: code_uart <= "2";
        4'b0010: code_uart <= "3";
        4'b0011: code_uart <= "A";
        4'b0100: code_uart <= "4";
        4'b0101: code_uart <= "5";
        4'b0110: code_uart <= "6";
        4'b0111: code_uart <= "B";
        4'b1000: code_uart <= "7";
        4'b1001: code_uart <= "8";
        4'b1010: code_uart <= "9";
        4'b1011: code_uart <= "C";
        4'b1100: code_uart <= "*";
        4'b1101: code_uart <= "0";
        4'b1110: code_uart <= "#";
        4'b1111: code_uart <= "D";
        default: code_uart <= "0";
    endcase
end
//localparam MEMORY_LENGTH = 2;

localparam TX_STATE_IDLE = 0;
localparam TX_STATE_START_BIT = 1;
localparam TX_STATE_WRITE = 2;
localparam TX_STATE_STOP_BIT = 3;
localparam TX_STATE_DEBOUNCE = 4;
always @(posedge clk)begin
    case (txState)
        TX_STATE_IDLE: begin
            if (KeyP == 0) begin //cuando se presiona una tecla
                txState <= TX_STATE_START_BIT;
                txCounter <= 0;
            end
            else begin
                txPinRegister <= 1;
            end
        end 
        TX_STATE_START_BIT: begin
            txPinRegister <= 0;
            if ((txCounter + 1) == DELAY_FRAMES) begin
                txState <= TX_STATE_WRITE;
                dataOut <= code_uart;// guardo el caracter
                txBitNumber <= 0;
                txCounter <= 0;
            end else 
                txCounter <= txCounter + 1;
        end
        TX_STATE_WRITE: begin
            txPinRegister <= dataOut[txBitNumber];
            if ((txCounter + 1) == DELAY_FRAMES) begin
                if (txBitNumber == 3'b111) begin // cuenta hasta 8bits
                    txState <= TX_STATE_STOP_BIT;
                end else begin
                    txState <= TX_STATE_WRITE;
                    txBitNumber <= txBitNumber + 1;
                end
                txCounter <= 0;
            end else 
                txCounter <= txCounter + 1;
        end
            TX_STATE_STOP_BIT: begin
            txPinRegister <= 1;
            if ((txCounter + 1) == DELAY_FRAMES) begin
                txState <= TX_STATE_DEBOUNCE;
                txCounter <= 0;
            end else 
                txCounter <= txCounter + 1;
        end
            TX_STATE_DEBOUNCE: begin
            if (txCounter == 23'b111111111111111111) begin
                if (KeyP == 1) 
                    txState <= TX_STATE_IDLE;
            end else
                txCounter <= txCounter + 1;
        end
    endcase
end

endmodule

Laboratorio_2/Ejercicio_2/Interfaz/sim/Interfaz_tb.sv
`timescale 1ms / 10ns

module Interfaz_tb();
reg KeyP;
reg clk;
reg rst;
reg uart_rx;
wire uart_tx;
reg [1:0] fila;
wire [3:0] Q;
wire [3:0] code;
wire [1:0] columna;

Interfaz I0(
    .KeyP(KeyP),
    .rst(rst),
    .clk(clk),
    .fila(fila),
    .uart_rx(uart_rx),
    .columna(columna),
    .Q(Q),
    .code(code),
    .uart_tx(uart_tx)
);

    always begin #0.000037037037 clk = ~clk;end

    initial begin
        rst = 0;
        fila=2'b0;
        KeyP=0;
        $monitor("[%0t] Salida Q=%b Codigo=%h Presionada=%h Fila=%h Columna=%h uart_Tx=%b",$time,Q,code,KeyP,fila,columna,uart_tx);
        for (int i =0 ;i<10 ;i++ ) begin
            #3 KeyP=1;
            fila =$random;
            #6 KeyP=0;
        end
        #10 $finish;
    end
    initial begin
        $dumpfile("Interfaz_tb.vcd");
        $dumpvars(0,Interfaz_tb);
    end
endmodule

Laboratorio_2/Ejercicio_2/Interfaz/build/Interfaz_tb.vcd
$date
	Thu Sep 19 18:28:27 2024
$end
$version
	Icarus Verilog
$end
$timescale
	10ns
$end
$scope module Interfaz_tb $end
$var wire 1 ! uart_tx $end
$var wire 2 " columna [1:0] $end
$var wire 4 # code [3:0] $end
$var wire 4 $ Q [3:0] $end
$var reg 1 % KeyP $end
$var reg 1 & clk $end
$var reg 2 ' fila [1:0] $end
$var reg 1 ( rst $end
$var reg 1 ) uart_rx $end
$scope module I0 $end
$var wire 1 % KeyP $end
$var wire 4 * Q [3:0] $end
$var wire 1 & clk $end
$var wire 2 + columna [1:0] $end
$var wire 2 , fila [1:0] $end
$var wire 1 ( rst $end
$var wire 1 ) uart_rx $end
$var wire 1 ! uart_tx $end
$var wire 1 - inhibit $end
$var wire 2 . columna1 [1:0] $end
$var wire 4 / Q1 [3:0] $end
$var wire 1 0 Data_Available $end
$var parameter 32 1 DELAY_FRAMES $end
$var parameter 32 2 HALF_DELAY_WAIT $end
$var parameter 32 3 TX_STATE_DEBOUNCE $end
$var parameter 32 4 TX_STATE_IDLE $end
$var parameter 32 5 TX_STATE_START_BIT $end
$var parameter 32 6 TX_STATE_STOP_BIT $end
$var parameter 32 7 TX_STATE_WRITE $end
$var reg 1 8 clk1 $end
$var reg 4 9 code [3:0] $end
$var reg 8 : code_uart [7:0] $end
$var reg 8 ; dataOut [7:0] $end
$var reg 3 < txBitNumber [2:0] $end
$var reg 25 = txCounter [24:0] $end
$var reg 1 > txPinRegister $end
$var reg 4 ? txState [3:0] $end
$scope module b0 $end
$var wire 1 % KeyP $end
$var reg 1 0 Data_Available $end
$var reg 1 - inhibit $end
$upscope $end
$scope module c0 $end
$var wire 1 8 clk $end
$var wire 1 - inhibit $end
$var reg 2 @ out [1:0] $end
$upscope $end
$scope module s0 $end
$var wire 1 A D0 $end
$var wire 1 B D1 $end
$var wire 1 C D2 $end
$var wire 1 D D3 $end
$var wire 1 0 clk $end
$var wire 1 ( rst $end
$var reg 4 E Q [3:0] $end
$upscope $end
$upscope $end
$scope begin $ivl_for_loop0 $end
$var integer 32 F i [31:0] $end
$upscope $end
$upscope $end
$enddefinitions $end
$comment Show the parameter values. $end
$dumpall
b10 7
b11 6
b1 5
b0 4
b100 3
b10101111110 2
b101011111100 1
$end
#0
$dumpvars
b0 F
bx E
xD
xC
0B
0A
bx @
b0 ?
1>
b0 =
b0 <
b0 ;
b110000 :
bx 9
x8
x0
bx /
bx .
1-
b0 ,
bx +
bx *
x)
0(
b0 '
x&
0%
bx $
bx #
bx "
1!
$end
#200000
b100 #
b100 9
b100 $
b100 *
b1011 /
b1011 E
10
#300000
b110100 :
1%
#500000
0-
00
#900000
1-
b1 F
0%
#1100000
10
#1200000
1A
b1 '
b1 ,
1%
#1400000
0-
00
#1800000
1-
b10 F
0%
#2000000
10
#2100000
1%
#2300000
0-
00
#2700000
1-
b11 F
0%
#2900000
10
#3000000
1B
b11 '
b11 ,
1%
#3200000
0-
00
#3600000
1-
b100 F
0%
#3800000
10
#3900000
0B
b1 '
b1 ,
1%
#4100000
0-
00
#4500000
1-
b101 F
0%
#4700000
10
#4800000
1%
#5000000
0-
00
#5400000
1-
b110 F
0%
#5600000
10
#5700000
1%
#5900000
0-
00
#6300000
1-
b111 F
0%
#6500000
10
#6600000
0A
1B
b10 '
b10 ,
1%
#6800000
0-
00
#7200000
1-
b1000 F
0%
#7400000
10
#7500000
1A
0B
b1 '
b1 ,
1%
#7700000
0-
00
#8100000
1-
b1001 F
0%
#8300000
10
#8400000
1%
#8600000
0-
00
#9000000
1-
b1010 F
0%
